bootstrap_resample/__init__.py
bootstrap_resample/pmap.py
bootstrap_resample/test.py
bootstrap_resample-0.1.dist-info/METADATA
bootstrap_resample-0.1.dist-info/WHEEL
bootstrap_resample-0.1.dist-info/top_level.txt
bootstrap_resample-0.1.dist-info/RECORD
